bing_images/__init__.py
bing_images/bing.py
bing_images/crawler.py
bing_images/util.py
bing_images-0.2.3.dist-info/LICENSE
bing_images-0.2.3.dist-info/METADATA
bing_images-0.2.3.dist-info/WHEEL
bing_images-0.2.3.dist-info/top_level.txt
bing_images-0.2.3.dist-info/RECORD
