Metadata-Version: 2.1
Name: bing-images
Version: 0.2.3
Summary: Python library to fetch image urls and download using multithreading from Bing.com.
Home-page: https://github.com/catchzeng/bing_images
Author: CatchZeng
Author-email: catchzenghh@gmail.com
Classifier: Programming Language :: Python :: 3
Classifier: License :: OSI Approved :: MIT License
Classifier: Operating System :: OS Independent
Requires-Python: >=3
License-File: LICENSE
